README.md
setup.py
leyuan/__init__.py
leyuan/do_cli.py
leyuan/do_init.py
leyuan/index.py
leyuan/utils.py
leyuan.egg-info/PKG-INFO
leyuan.egg-info/SOURCES.txt
leyuan.egg-info/dependency_links.txt
leyuan.egg-info/entry_points.txt
leyuan.egg-info/requires.txt
leyuan.egg-info/top_level.txt
leyuan/daemon_lib/__init__.py
leyuan/daemon_lib/pull_upstream.py
leyuan/daemon_lib/push_upstream.py