Metadata-Version: 1.0
Name: leyuan
Version: 1.0.0
Summary: Leyuan Cluster Tool
Home-page: https://github.com/qorzj/leyuan
Author: qorzj
Author-email: inull@qq.com
License: MIT
Keywords: lesscli
Platform: any
